{
  "hero": {
    "headingLine1": "Heal. Restore.",
    "headingLine2": "Bee Relieved.",
    "subtext": "Registered massage and manual osteopathic therapy tailored to your body's unique needs. Treating the root cause of your discomfort, not just the symptoms.",
    "ctaPrimaryLabel": "Book Online",
    "ctaSecondaryLabel": "Text or call: (306) 852-7969",
    "heroImage": "/uploads/JPEG%20image.jpeg"
  },
  "about": {
    "therapistName": "Chloe",
    "therapistNameItalic": "Jackson-Kotko",
    "bio": "Hi there!! I'm a passionate Registered Massage Therapist and Manual Osteopathic Therapist based in Saskatoon, SK. I specialize in therapeutic treatment that works with all systems of the body to find the root cause of your pain or dysfunction. Whether you're dealing with chronic tension, injury recovery, postural issues, or stress, I strive to create a personalized treatment plan to help rid you of your discomfort! ",
    "photo": "/uploads/JPEG image 6.jpeg",
    "credentials": "Registered Massage Therapist (RMT) & Manual Osteopathic Therapist (MOT)",
    "location": "Integrative Therapies Health Collective, 1647 29th St W, Saskatoon, SK",
    "contactNote": "Texting gets the fastest response!"
  },
  "bookingCta": {
    "heading": "Book Your Session",
    "headingItalic": "Today",
    "subtext": "Online booking is fast and easy through Jane App. Prefer to reach out first? Text us for the fastest response."
  }
}